py_motion_detector/__init__.py
py_motion_detector/cli.py
py_motion_detector/main.py
py_motion_detector-0.1.2.dist-info/entry_points.txt
py_motion_detector-0.1.2.dist-info/LICENSE
py_motion_detector-0.1.2.dist-info/WHEEL
py_motion_detector-0.1.2.dist-info/METADATA
py_motion_detector-0.1.2.dist-info/RECORD
